{
    "bounds": "[44,608][1036,911]", 
    "checkable": false, 
    "checked": false, 
    "class": "android.view.ViewGroup", 
    "clickable": true, 
    "enabled": true, 
    "focusable": true, 
    "focused": false, 
    "hash": "gYp8nLB3V9y5yWWzlLpW7A==\n", 
    "height": 303, 
    "hier_level": 18, 
    "human_hash": "android.view.ViewGroup_X44_Y608_W992_H303", 
    "human_readable": "android.view.ViewGroup_44_608_992_303_android.view.ViewGroup_f800f800f800f800f800ffc0fbc0f800fb00f800fae0fa40f800f800f800f800_08712b65d642da3cf770d2b2f3468cb8", 
    "image_path": "ZDNmYjU3YTU0Zjk0MGQyNjgzMTZhN2Y0OGIzMmM1MTE.png", 
    "index": "0", 
    "is_transformed": true, 
    "long-clickable": false, 
    "password": false, 
    "screen_hash": "71be8f8ed702871507eadde4c836cfd4", 
    "scrollable": false, 
    "selected": false, 
    "tag_name": "android.view.ViewGroup", 
    "text": "30:00 Free Your Mind Cycling Claire J. SoulCycle", 
    "width": 992, 
    "x": 44, 
    "y": 608
}